README.md
setup.py
qhue/__init__.py
qhue/oauth_receiver.py
qhue/qhue.py
qhue/qhue_remote.py
qhue.egg-info/PKG-INFO
qhue.egg-info/SOURCES.txt
qhue.egg-info/dependency_links.txt
qhue.egg-info/pbr.json
qhue.egg-info/requires.txt
qhue.egg-info/top_level.txt