Metadata-Version: 2.1
Name: qhue
Version: 2.0.1
Summary: Qhue: python wrapper for Philips Hue API
Home-page: https://github.com/quentinsf/qhue
Author: Quentin Stafford-Fraser
License: GNU GPL 2
Platform: UNKNOWN
Requires-Python: >3.4
